[
  {"city_name_en": "Riyadh", "code": "11564", "place_name_en": "Olaya", "place_name_ar": "العليا"},
  {"city_name_en": "Riyadh", "code": "12211", "place_name_en": "Al Malaz", "place_name_ar": "الملز"},
  {"city_name_en": "Riyadh", "code": "13241", "place_name_en": "Al Nakheel", "place_name_ar": "النخيل"},
  {"city_name_en": "Riyadh", "code": "13321", "place_name_en": "King Fahd District", "place_name_ar": "حي الملك فهد"},
  {"city_name_en": "Jeddah", "code": "21423", "place_name_en": "Al Balad", "place_name_ar": "البلد"},
  {"city_name_en": "Jeddah", "code": "21577", "place_name_en": "Al Zahra", "place_name_ar": "الزهراء"},
  {"city_name_en": "Jeddah", "code": "23421", "place_name_en": "Obhur", "place_name_ar": "أبحر"},
  {"city_name_en": "Makkah", "code": "24231", "place_name_en": "Makkah", "place_name_ar": "مكة المكرمة"},
  {"city_name_en": "Madinah", "code": "42311", "place_name_en": "Madinah", "place_name_ar": "المدينة المنورة"},
  {"city_name_en": "Dammam", "code": "32241", "place_name_en": "Dammam", "place_name_ar": "الدمام"},
  {"city_name_en": "Khobar", "code": "34421", "place_name_en": "Al Khobar", "place_name_ar": "الخبر"},
  {"city_name_en": "Al Khobar", "code": "34421", "place_name_en": "Al Khobar", "place_name_ar": "الخبر"},
  {"city_name_en": "Dhahran", "code": "34464", "place_name_en": "Dhahran", "place_name_ar": "الظهران"},
  {"city_name_en": "Taif", "code": "26513", "place_name_en": "Taif", "place_name_ar": "الطائف"},
  {"city_name_en": "Tabuk", "code": "71421", "place_name_en": "Tabuk", "place_name_ar": "تبوك"},
  {"city_name_en": "Abha", "code": "62521", "place_name_en": "Abha", "place_name_ar": "أبها"},
  {"city_name_en": "Khamis Mushait", "code": "62451", "place_name_en": "Khamis Mushait", "place_name_ar": "خميس مشيط"},
  {"city_name_en": "Hail", "code": "55421", "place_name_en": "Hail", "place_name_ar": "حائل"},
  {"city_name_en": "Najran", "code": "66241", "place_name_en": "Najran", "place_name_ar": "نجران"},
  {"city_name_en": "Jazan", "code": "45142", "place_name_en": "Jazan", "place_name_ar": "جازان"},
  {"city_name_en": "Buraidah", "code": "51411", "place_name_en": "Buraidah", "place_name_ar": "بريدة"},
  {"city_name_en": "Jubail", "code": "31951", "place_name_en": "Jubail", "place_name_ar": "الجبيل"},
  {"city_name_en": "Yanbu", "code": "46421", "place_name_en": "Yanbu", "place_name_ar": "ينبع"}
]
